ggghhhrrr/__init__.py
ggghhhrrr-0.3.dist-info/METADATA
ggghhhrrr-0.3.dist-info/WHEEL
ggghhhrrr-0.3.dist-info/entry_points.txt
ggghhhrrr-0.3.dist-info/top_level.txt
ggghhhrrr-0.3.dist-info/RECORD
